udata_koumoul/__init__.py
udata_koumoul/info.json
udata_koumoul/static/admin.css
udata_koumoul/static/theme.css
udata_koumoul/static/img/koumoul-transparent-256.png
udata_koumoul/static/img/smart-city.jpg
udata_koumoul/static/img/flags/de.png
udata_koumoul/static/img/flags/en.png
udata_koumoul/static/img/flags/es.png
udata_koumoul/static/img/flags/fr.png
udata_koumoul/static/img/flags/unknown.png
udata_koumoul/static/img/placeholders/default.png
udata_koumoul/static/img/placeholders/organization.png
udata_koumoul/static/img/placeholders/post.png
udata_koumoul/static/img/placeholders/reuse.png
udata_koumoul/static/img/placeholders/user.png
udata_koumoul/templates/footer.html
udata_koumoul/templates/header.html
udata_koumoul/templates/home.html
udata_koumoul/templates/raw.html
udata_koumoul/templates/dataset/display.html
udata_koumoul/templates/dataset/resource/card.html
udata_koumoul/templates/organization/display.html
udata_koumoul/templates/reuse/card.html
udata_koumoul/templates/reuse/display.html
udata_koumoul/templates/sections/datasets.html
udata_koumoul/templates/sections/last-post.html
udata_koumoul/templates/sections/reuses.html
udata_koumoul-0.4.0.dist-info/DESCRIPTION.rst
udata_koumoul-0.4.0.dist-info/METADATA
udata_koumoul-0.4.0.dist-info/RECORD
udata_koumoul-0.4.0.dist-info/WHEEL
udata_koumoul-0.4.0.dist-info/entry_points.txt
udata_koumoul-0.4.0.dist-info/metadata.json
udata_koumoul-0.4.0.dist-info/top_level.txt
