Metadata-Version: 2.0
Name: udata-koumoul
Version: 0.4.0
Summary: Theme for Koumoul demo opendata portal
Home-page: https://demo.koumoul.com
Author: Koumoul
Author-email: contact@koumoul.com
License: MIT
Keywords: u,d,a,t,a,,, ,t,h,e,m,e,,, ,u,d,a,t,a,-,k,o,u,m,o,u,l
Platform: UNKNOWN
Classifier: Development Status :: 3 - Alpha
Classifier: Programming Language :: Python
Classifier: Environment :: Web Environment
Classifier: Operating System :: OS Independent
Classifier: Intended Audience :: Developers
Classifier: Topic :: System :: Software Distribution
Classifier: Programming Language :: Python
Classifier: Programming Language :: Python :: 2
Classifier: Programming Language :: Python :: 2.7
Classifier: Topic :: Software Development :: Libraries :: Python Modules
